goslideapi/__init__.py
goslideapi/goslideapi.py
goslideapi/test.py
goslide_api-0.7.4.dist-info/LICENSE
goslide_api-0.7.4.dist-info/METADATA
goslide_api-0.7.4.dist-info/WHEEL
goslide_api-0.7.4.dist-info/top_level.txt
goslide_api-0.7.4.dist-info/RECORD
