Metadata-Version: 2.1
Name: goslide-api
Version: 0.7.4
Summary: Python API to utilise the Slide Open Cloud and Local API
Home-page: https://github.com/ualex73/goslide-api
Author: Alexander Kuiper
Author-email: ualex73@gmail.com
License: Apache License 2.0
Platform: UNKNOWN
Classifier: Programming Language :: Python :: 3.7
Classifier: Programming Language :: Python :: 3.8
Classifier: Programming Language :: Python :: 3.9
Classifier: Programming Language :: Python :: 3.10
Classifier: Programming Language :: Python :: 3.11
Classifier: Programming Language :: Python :: 3.12
Classifier: Programming Language :: Python :: 3.13
Classifier: License :: OSI Approved :: Apache Software License
Classifier: Operating System :: OS Independent
Requires-Python: >=3.5.2
